niklibrary/__init__.py
niklibrary/build/Overlay.py
niklibrary/build/__init__.py
niklibrary/compression/Modes.py
niklibrary/compression/Tar.py
niklibrary/compression/Zip.py
niklibrary/compression/Zsh.py
niklibrary/compression/__init__.py
niklibrary/configuration/Config.py
niklibrary/configuration/__init__.py
niklibrary/extract/ExtractOp.py
niklibrary/extract/__init__.py
niklibrary/git/Git.py
niklibrary/git/GitOp.py
niklibrary/git/GitStatics.py
niklibrary/git/GithubManager.py
niklibrary/git/GitlabManager.py
niklibrary/git/__init__.py
niklibrary/helper/Assets.py
niklibrary/helper/B64.py
niklibrary/helper/C.py
niklibrary/helper/Cmd.py
niklibrary/helper/F.py
niklibrary/helper/P.py
niklibrary/helper/Statics.py
niklibrary/helper/SystemStat.py
niklibrary/helper/T.py
niklibrary/helper/XmlOp.py
niklibrary/helper/__init__.py
niklibrary/json/Json.py
niklibrary/json/__init__.py
niklibrary/json/filter_conversation.py
niklibrary/oem/AndroidDump.py
niklibrary/oem/GoogleOem.py
niklibrary/oem/OemOp.py
niklibrary/oem/__init__.py
niklibrary/web/Download.py
niklibrary/web/GoFileUpload.py
niklibrary/web/Requests.py
niklibrary/web/TelegramApi.py
niklibrary/web/Upload.py
niklibrary/web/UploadCmd.py
niklibrary/web/__init__.py
niklibrary-0.51.dist-info/METADATA
niklibrary-0.51.dist-info/WHEEL
niklibrary-0.51.dist-info/entry_points.txt
niklibrary-0.51.dist-info/top_level.txt
niklibrary-0.51.dist-info/RECORD
